outsetapy/__init__.py
outsetapy/static.py
outsetapy/api/__inti__.py
outsetapy/api/billing/__init__.py
outsetapy/api/billing/invoices.py
outsetapy/api/billing/plan_families.py
outsetapy/api/billing/plans.py
outsetapy/api/billing/subscriptions.py
outsetapy/api/billing/transactions.py
outsetapy/api/billing/usage.py
outsetapy/api/crm/__init__.py
outsetapy/api/crm/accounts.py
outsetapy/api/crm/activities.py
outsetapy/api/crm/deals.py
outsetapy/api/crm/people.py
outsetapy/api/marketing/__init__.py
outsetapy/api/marketing/email_list_subscriptions.py
outsetapy/api/support/__init__.py
outsetapy/api/support/cases.py
outsetapy/api/user/__init__.py
outsetapy/api/user/password.py
outsetapy/api/user/profile.py
outsetapy/models/__init__.py
outsetapy/models/billing/add_on.py
outsetapy/models/billing/billing_add_on_type.py
outsetapy/models/billing/billing_renewal_term.py
outsetapy/models/billing/billing_transaction_type.py
outsetapy/models/billing/charge_summary.py
outsetapy/models/billing/invoice.py
outsetapy/models/billing/invoice_display_item.py
outsetapy/models/billing/invoice_line_item.py
outsetapy/models/billing/plan.py
outsetapy/models/billing/plan_add_on.py
outsetapy/models/billing/plan_family.py
outsetapy/models/billing/subscription.py
outsetapy/models/billing/subscription_add_on.py
outsetapy/models/billing/transaction.py
outsetapy/models/billing/usage_item.py
outsetapy/models/crm/account.py
outsetapy/models/crm/account_stage.py
outsetapy/models/crm/activity.py
outsetapy/models/crm/activity_type.py
outsetapy/models/crm/deal.py
outsetapy/models/crm/deal_person.py
outsetapy/models/crm/deal_pipeline.py
outsetapy/models/crm/deal_pipeline_stage.py
outsetapy/models/crm/person.py
outsetapy/models/crm/person_account.py
outsetapy/models/marketing/email_list_person.py
outsetapy/models/marketing/emaillist.py
outsetapy/models/shared/address.py
outsetapy/models/shared/entity.py
outsetapy/models/support/case.py
outsetapy/models/support/case_history.py
outsetapy-0.1.5.dist-info/METADATA
outsetapy-0.1.5.dist-info/WHEEL
outsetapy-0.1.5.dist-info/top_level.txt
outsetapy-0.1.5.dist-info/RECORD
