Metadata-Version: 2.1
Name: outsetapy
Version: 0.1.5
Summary: A SDK for building applications with Outseta
Author-email: "Roborian, Inc" <info@roborian.com>
Project-URL: Homepage, https://github.com/Roborian/outsetapy
Project-URL: Issues, https://github.com/Roborian/outsetapy/issues
Classifier: Programming Language :: Python :: 3
Classifier: License :: OSI Approved :: MIT License
Classifier: Operating System :: OS Independent
Requires-Python: >=3.8
